stoobly_orator/__init__.py
stoobly_orator/commands/__init__.py
stoobly_orator/commands/application.py
stoobly_orator/commands/command.py
stoobly_orator/commands/migrations/__init__.py
stoobly_orator/commands/migrations/base_command.py
stoobly_orator/commands/migrations/install_command.py
stoobly_orator/commands/migrations/make_command.py
stoobly_orator/commands/migrations/migrate_command.py
stoobly_orator/commands/migrations/refresh_command.py
stoobly_orator/commands/migrations/reset_command.py
stoobly_orator/commands/migrations/rollback_command.py
stoobly_orator/commands/migrations/status_command.py
stoobly_orator/commands/models/__init__.py
stoobly_orator/commands/models/make_command.py
stoobly_orator/commands/models/stubs.py
stoobly_orator/commands/seeds/__init__.py
stoobly_orator/commands/seeds/base_command.py
stoobly_orator/commands/seeds/make_command.py
stoobly_orator/commands/seeds/seed_command.py
stoobly_orator/connections/__init__.py
stoobly_orator/connections/connection.py
stoobly_orator/connections/connection_interface.py
stoobly_orator/connections/connection_resolver_interface.py
stoobly_orator/connections/mysql_connection.py
stoobly_orator/connections/postgres_connection.py
stoobly_orator/connections/sqlite_connection.py
stoobly_orator/connectors/__init__.py
stoobly_orator/connectors/connection_factory.py
stoobly_orator/connectors/connector.py
stoobly_orator/connectors/mysql_connector.py
stoobly_orator/connectors/postgres_connector.py
stoobly_orator/connectors/sqlite_connector.py
stoobly_orator/database_manager.py
stoobly_orator/dbal/__init__.py
stoobly_orator/dbal/abstract_asset.py
stoobly_orator/dbal/column.py
stoobly_orator/dbal/column_diff.py
stoobly_orator/dbal/comparator.py
stoobly_orator/dbal/exceptions/__init__.py
stoobly_orator/dbal/foreign_key_constraint.py
stoobly_orator/dbal/identifier.py
stoobly_orator/dbal/index.py
stoobly_orator/dbal/mysql_schema_manager.py
stoobly_orator/dbal/platforms/__init__.py
stoobly_orator-0.9.12.dist-info/LICENSE
stoobly_orator-0.9.12.dist-info/METADATA
stoobly_orator-0.9.12.dist-info/WHEEL
stoobly_orator-0.9.12.dist-info/entry_points.txt
stoobly_orator-0.9.12.dist-info/RECORD
